distro_probability/Binomialdistribution.py
distro_probability/Gaussiandistribution.py
distro_probability/Generaldistribution.py
distro_probability/__init__.py
distro_probability-0.1.dist-info/DESCRIPTION.rst
distro_probability-0.1.dist-info/METADATA
distro_probability-0.1.dist-info/RECORD
distro_probability-0.1.dist-info/WHEEL
distro_probability-0.1.dist-info/metadata.json
distro_probability-0.1.dist-info/top_level.txt
