Metadata-Version: 2.0
Name: distro-probability
Version: 0.1
Summary: Gaussian distributions
Home-page: UNKNOWN
Author: Ernest Abah
Author-email: abahernesto@gmail.com
License: UNKNOWN
Platform: UNKNOWN
